securechat/__init__.py
securechat/cli.py
securechat/client.py
securechat/crypto.py
securechat/database.py
securechat/server.py
securechat_py-1.0.2.dist-info/METADATA
securechat_py-1.0.2.dist-info/WHEEL
securechat_py-1.0.2.dist-info/entry_points.txt
securechat_py-1.0.2.dist-info/licenses/LICENSE
securechat_py-1.0.2.dist-info/RECORD
