Metadata-Version: 2.4
Name: securechat-py
Version: 1.0.2
Summary: Ultra-secure terminal-based chat with end-to-end encryption and decentralized networking
Project-URL: Homepage, https://github.com/i-soumya18/securechat
Project-URL: Documentation, https://github.com/i-soumya18/securechat#readme
Project-URL: Repository, https://github.com/i-soumya18/securechat
Project-URL: Bug Reports, https://github.com/i-soumya18/securechat/issues
Author-email: Soumyaranjan sahoo <sahoosoumya242004@gmail.com>
License: MIT
License-File: LICENSE
Keywords: chat,decentralized,encryption,messaging,security,terminal
Classifier: Development Status :: 5 - Production/Stable
Classifier: Intended Audience :: End Users/Desktop
Classifier: License :: OSI Approved :: MIT License
Classifier: Operating System :: OS Independent
Classifier: Programming Language :: Python :: 3
Classifier: Programming Language :: Python :: 3.8
Classifier: Programming Language :: Python :: 3.9
Classifier: Programming Language :: Python :: 3.10
Classifier: Programming Language :: Python :: 3.11
Classifier: Programming Language :: Python :: 3.12
Classifier: Programming Language :: Python :: 3.13
Classifier: Topic :: Communications :: Chat
Classifier: Topic :: Security :: Cryptography
Requires-Python: >=3.8
Requires-Dist: cryptography>=3.4.0
